setup.py
vimwiki_tools/__init__.py
vimwiki_tools.egg-info/PKG-INFO
vimwiki_tools.egg-info/SOURCES.txt
vimwiki_tools.egg-info/dependency_links.txt
vimwiki_tools.egg-info/entry_points.txt
vimwiki_tools.egg-info/requires.txt
vimwiki_tools.egg-info/top_level.txt