Metadata-Version: 1.0
Name: vimwiki-tools
Version: 0.0.2
Summary: tools for vimwiki
Home-page: https://github.com/zweifisch/vimwiki-tools
Author: Feng Zhou
Author-email: zf.pascal@gmail.com
License: UNKNOWN
Platform: UNKNOWN
